tangled_mcp/__init__.py
tangled_mcp/__main__.py
tangled_mcp/py.typed
tangled_mcp/server.py
tangled_mcp/settings.py
tangled_mcp/_tangled/__init__.py
tangled_mcp/_tangled/_client.py
tangled_mcp/_tangled/_issues.py
tangled_mcp/types/__init__.py
tangled_mcp/types/_branches.py
tangled_mcp/types/_common.py
tangled_mcp/types/_issues.py
tangled_mcp-0.0.14.dist-info/METADATA
tangled_mcp-0.0.14.dist-info/WHEEL
tangled_mcp-0.0.14.dist-info/entry_points.txt
tangled_mcp-0.0.14.dist-info/RECORD
