Metadata-Version: 2.4
Name: tangled-mcp
Version: 0.0.14
Summary: MCP server for Tangled git collaboration platform
Author-email: nate <zzstoatzz@protonmail.com>
Requires-Python: >=3.10
Requires-Dist: atproto
Requires-Dist: fastmcp>=2.12.4
Requires-Dist: httpx>=0.28.1
Requires-Dist: pydantic-settings>=2.11.0
Requires-Dist: python-dotenv>=1.1.1
Requires-Dist: websockets>=15.0.1
